{"cameraMode":{"drawMode":0,"name":"Shaded","section":"Shading Mode"},"sceneLighting":true,"audioPlay":false,"sceneViewState":{"m_AlwaysRefresh":false,"showFog":true,"showSkybox":true,"showFlares":true,"showImageEffects":true,"showParticleSystems":true,"showVisualEffectGraphs":true,"m_FxEnabled":true},"in2DMode":false,"pivot":{"x":56239.39453125,"y":-2836.69921875,"z":-16708.74609375},"rotation":{"x":0.0842684805393219,"y":0.8917897939682007,"z":-0.18618270754814149,"w":0.4037400484085083},"size":76258.765625,"orthographic":false}